ba_lorre/__init__.py
ba_lorre/lorre.py
ba_lorre/pruning_functions.py
ba_lorre-1.0.2.dist-info/LICENSE
ba_lorre-1.0.2.dist-info/METADATA
ba_lorre-1.0.2.dist-info/WHEEL
ba_lorre-1.0.2.dist-info/top_level.txt
ba_lorre-1.0.2.dist-info/RECORD
